README.md
setup.cfg
setup.py
jsonapidb/__init__.py
jsonapidb.egg-info/PKG-INFO
jsonapidb.egg-info/SOURCES.txt
jsonapidb.egg-info/dependency_links.txt
jsonapidb.egg-info/requires.txt
jsonapidb.egg-info/top_level.txt
jsonapidb/api/__init__.py
jsonapidb/api/context_producers.py
jsonapidb/api/errors_context_producers.py
jsonapidb/api/handlers.py
jsonapidb/builders/__init__.py
jsonapidb/builders/app_builder.py
jsonapidb/builders/json_proxy.py
jsonapidb/builders/json_schema.py
jsonapidb/builders/scrambler.py
jsonapidb/conversion/__init__.py
jsonapidb/conversion/converters.py
jsonapidb/dto/__init__.py
jsonapidb/dto/output.py
jsonapidb/model/__init__.py
jsonapidb/model/core.py
jsonapidb/model/domain.py
jsonapidb/model/repository/__init__.py
jsonapidb/model/repository/engine_registry.py
jsonapidb/model/repository/query.py
jsonapidb/model/repository/relations_repository.py
jsonapidb/model/repository/repository.py
jsonapidb/model/validators/__init__.py
jsonapidb/model/validators/attr_validation.py
jsonapidb/model/validators/relations_validation.py
jsonapidb/model/validators/validator.py
jsonapidb/serialization/__init__.py
jsonapidb/serialization/utils.py
jsonapidb/serialization/deserialiers/__init__.py
jsonapidb/serialization/deserialiers/entity_instance_deserializers.py
jsonapidb/serialization/deserialiers/relation_instance_deserializers.py
jsonapidb/serialization/serializers/__init__.py
jsonapidb/serialization/serializers/dedicated.py
jsonapidb/serialization/serializers/entity_instance_serializers.py
jsonapidb/serialization/serializers/error_serializers.py
jsonapidb/serialization/serializers/relation_instance_serializer.py