Metadata-Version: 1.1
Name: jsonapidb
Version: 0.1.6
Summary: json api interface for mongodb
Home-page: https://github.com/prototype-project/jsonapidb
Author: prototype-organisation
Author-email: beczkowb@gmail.com
License: UNKNOWN
Download-URL: https://github.com/prototype-project/prototype/archive/0.1.6.tar.gz
Keywords: jsonapi,nosql,mongodb,database
Platform: UNKNOWN
